{
  "name": "node3-send-mail",
  "description": "Sidecar is for mocking. To check what is going on at mailhog: kubectl port-forward node3-send-mail-gxfts-dzbdv 8025:8025 and go to http://localhost:8025/#",
  "volumes": [],
  "cpu": 1,
  "gpu": 0,
  "mem": "256Mi",
  "workerEnv": {},
  "algorithmEnv": {
    "NOTIFY_WS_URL": "ws://localhost:5000/ws",
    "SMTP_HOST": "localhost",
    "SMTP_PORT": "1025",
    "SMTP_FROM": "example@gmail.com"
  },
  "sideCars": [
    {
      "container": {
        "name": "ws-mock-service",
        "image": "hkubedevtest/ws-service:yuut9wlmu"
      },
      "environments": {
        "MOCK_PORT": "5000"
      }
    },
    {
      "container": {
        "name": "mailhog",
        "image": "mailhog/mailhog:latest",
        "ports": [
          {
            "containerPort": 1025
          },
          {
            "containerPort": 8025
          }
        ]
      },
      "environments": {}
    }
  ],
  "reservedMemory": "512Mi",
  "minHotWorkers": 1,
  "options": {
    "pending": false
  },
  "env": "python",
  "entryPoint": "send_mail.py",
  "type": "Code",
  "fileInfo": {
    "fileExt": "gz",
    "checksum": "df7408d1812b52b1f6801a15e7f337066c58764a",
    "fileSize": 1433,
    "path": "dev1-spot-hkube-builds/node3-send-mail-bi09xt"
  },
  "algorithmImage": "docker.io/hkubedevtest/node3-send-mail:vlw3s0qxv",
  "version": "eh9xrls3a9",
  "created": 1757400847173,
  "modified": 1757494783237,
  "auditTrail": [
    {
      "user": "defaultUser",
      "timestamp": 1757494783237,
      "version": "eh9xrls3a9"
    },
    {
      "user": "defaultUser",
      "timestamp": 1757494622199,
      "version": "fiwvf1q8in"
    },
    {
      "user": "defaultUser",
      "timestamp": 1757494615172,
      "version": "fiwvf1q8in"
    },
    {
      "user": "defaultUser",
      "timestamp": 1757492809871,
      "version": "iwnibv6n7x"
    },
    {
      "user": "defaultUser",
      "timestamp": 1757492192399,
      "version": "hefaitq0aa"
    },
    {
      "user": "defaultUser",
      "timestamp": 1757492065109,
      "version": "ie4aud981r"
    },
    {
      "user": "defaultUser",
      "timestamp": 1757492016258,
      "version": "c4we4x8kqs"
    },
    {
      "user": "defaultUser",
      "timestamp": 1757490969848,
      "version": "c4mf786gxm"
    },
    {
      "user": "defaultUser",
      "timestamp": 1757489779604,
      "version": "vyo1mwxg0w"
    },
    {
      "user": "defaultUser",
      "timestamp": 1757486601531,
      "version": "61bcaxy9ij"
    },
    {
      "user": "defaultUser",
      "timestamp": 1757429757077,
      "version": "ce67tx5dts"
    },
    {
      "user": "defaultUser",
      "timestamp": 1757428579929,
      "version": "rtinphtfim"
    },
    {
      "user": "defaultUser",
      "timestamp": 1757428255943,
      "version": "3osu5fwhw2"
    },
    {
      "user": "defaultUser",
      "timestamp": 1757426625613,
      "version": "j1o8tq4ln8"
    },
    {
      "user": "defaultUser",
      "timestamp": 1757426482605,
      "version": "y23p19kgi8"
    },
    {
      "user": "defaultUser",
      "timestamp": 1757423584437,
      "version": "4ss0t5sgz6"
    },
    {
      "user": "defaultUser",
      "timestamp": 1757422985436,
      "version": "y7ojpjavgt"
    },
    {
      "user": "defaultUser",
      "timestamp": 1757422301845,
      "version": "rsg9hfhns5"
    },
    {
      "user": "defaultUser",
      "timestamp": 1757422261519,
      "version": "1zd6rgudvj"
    },
    {
      "user": "defaultUser",
      "timestamp": 1757421790500,
      "version": "1o7suv464m"
    },
    {
      "user": "defaultUser",
      "timestamp": 1757420569827,
      "version": "gwt732nogb"
    },
    {
      "user": "defaultUser",
      "timestamp": 1757420033790,
      "version": "1csdc00b05"
    },
    {
      "user": "defaultUser",
      "timestamp": 1757415691792,
      "version": "x3ikdfl7pu"
    },
    {
      "user": "defaultUser",
      "timestamp": 1757414462505,
      "version": "e1namykheo"
    },
    {
      "user": "defaultUser",
      "timestamp": 1757414379887,
      "version": "9nhu16zpg7"
    }
  ]
}